tensorbox/__init__.py
tensorbox-0.0.1.dist-info/METADATA
tensorbox-0.0.1.dist-info/WHEEL
tensorbox-0.0.1.dist-info/licenses/LICENSE
tensorbox-0.0.1.dist-info/RECORD
