Metadata-Version: 2.3
Name: tensorbox
Version: 0.0.1
Summary: Type annotations and runtime checking for dataclass-like containers of tensors.
Project-URL: repository, https://github.com/dcharatan/tensorbox
Author-email: David Charatan <charatan@mit.edu>
License: MIT License
License-File: LICENSE
Keywords: deep-learning,neural-networks,pytorch,typing
Classifier: Development Status :: 3 - Alpha
Classifier: Intended Audience :: Developers
Classifier: Intended Audience :: Financial and Insurance Industry
Classifier: Intended Audience :: Information Technology
Classifier: Intended Audience :: Science/Research
Classifier: License :: OSI Approved :: MIT License
Classifier: Natural Language :: English
Classifier: Programming Language :: Python :: 3
Classifier: Topic :: Scientific/Engineering :: Artificial Intelligence
Classifier: Topic :: Scientific/Engineering :: Information Analysis
Classifier: Topic :: Scientific/Engineering :: Mathematics
Requires-Python: ~=3.11
Requires-Dist: beartype>=0.17.2
Requires-Dist: jaxtyping>=0.2.28
Requires-Dist: numpy>=1.20.0
Requires-Dist: torch>=2.0.0
